instances/__init__.py
instances/admin.py
instances/fields.py
instances/forms.py
instances/middleware.py
instances/models.py
instances/tests.py
instances/urls.py
instances/views.py
instances/locale/en/LC_MESSAGES/django.po
instances/locale/es/LC_MESSAGES/django.mo
instances/locale/es/LC_MESSAGES/django.po
instances/migrations/0001_initial.py
instances/migrations/0002_auto_20151001_1132.py
instances/migrations/__init__.py
instances/templates/instances/index.html
instances/templates/instances/instance_form.html
django_subdomain_instances-3.0.2.dist-info/METADATA
django_subdomain_instances-3.0.2.dist-info/WHEEL
django_subdomain_instances-3.0.2.dist-info/top_level.txt
django_subdomain_instances-3.0.2.dist-info/RECORD
