Metadata-Version: 2.1
Name: django-subdomain-instances
Version: 3.0.2
Summary: A way of allowing subdomains to be served by the same project, and associating objects with particular subdomains.
Home-page: https://github.com/mysociety/django-subdomain-instances
Author: mySociety
Author-email: matthew@mysociety.org
License: UNKNOWN
Platform: UNKNOWN
Classifier: Framework :: Django
Classifier: Programming Language :: Python :: 2
Classifier: Programming Language :: Python :: 3
Requires-Dist: Django (>=1.11)
